screen_times/__init__.py
screen_times/cli.py
screen_times/jsonl_manager.py
screen_times/ocr.py
screen_times/record_merger.py
screen_times/screen_ocr_logger.py
screen_times/screenshot.py
screen_times/screenshot_ocr.py
screen_times/split_jsonl.py
screen_times/resources/screenshot_window.applescript
screen_times-0.4.2.dist-info/licenses/LICENSE
screen_times-0.4.2.dist-info/METADATA
screen_times-0.4.2.dist-info/WHEEL
screen_times-0.4.2.dist-info/entry_points.txt
screen_times-0.4.2.dist-info/top_level.txt
screen_times-0.4.2.dist-info/RECORD
