Metadata-Version: 2.4
Name: screen-times
Version: 0.4.2
Summary: macOS screen activity logger with OCR using Vision Framework
Author-email: Kobori Akira <private.beats@gmail.com>
Maintainer-email: Kobori Akira <private.beats@gmail.com>
License-Expression: MIT
Project-URL: Homepage, https://github.com/koboriakira/screen-times
Project-URL: Repository, https://github.com/koboriakira/screen-times
Project-URL: Issues, https://github.com/koboriakira/screen-times/issues
Project-URL: Changelog, https://github.com/koboriakira/screen-times/releases
Keywords: ocr,screenshot,macos,logging,productivity,vision-framework,activity-tracking
Classifier: Development Status :: 3 - Alpha
Classifier: Environment :: MacOS X
Classifier: Intended Audience :: End Users/Desktop
Classifier: Intended Audience :: Developers
Classifier: Operating System :: MacOS
Classifier: Programming Language :: Python :: 3
Classifier: Programming Language :: Python :: 3.9
Classifier: Programming Language :: Python :: 3.10
Classifier: Programming Language :: Python :: 3.11
Classifier: Programming Language :: Python :: 3.12
Classifier: Programming Language :: Python :: 3.13
Classifier: Programming Language :: Python :: 3.14
Classifier: Topic :: Desktop Environment :: Screen Savers
Classifier: Topic :: System :: Logging
Classifier: Topic :: Utilities
Requires-Python: >=3.9
License-File: LICENSE
Requires-Dist: pyobjc-framework-Cocoa>=12.0; sys_platform == "darwin"
Requires-Dist: pyobjc-framework-Vision>=12.0; sys_platform == "darwin"
Requires-Dist: pyobjc-framework-Quartz>=12.0; sys_platform == "darwin"
Requires-Dist: rapidfuzz>=3.0.0
Provides-Extra: dev
Requires-Dist: black>=23.0.0; extra == "dev"
Requires-Dist: mypy>=1.0.0; extra == "dev"
Requires-Dist: pytest>=7.0.0; extra == "dev"
Requires-Dist: pytest-cov>=4.0.0; extra == "dev"
Requires-Dist: flake8>=6.0.0; extra == "dev"
Requires-Dist: pillow>=10.0.0; extra == "dev"
Requires-Dist: pre-commit>=3.0.0; extra == "dev"
Dynamic: license-file
